{
	"parent": "item/generated",
	"textures": {
	 "layer0": "item/carved_pumpkin"
	},
	
	"overrides": [
	 {"predicate": {"custom_model_data":1}, "model": "block/hammerflag"},
	 {"predicate": {"custom_model_data":2}, "model": "block/beeflag"},
	 {"predicate": {"custom_model_data":3}, "model": "block/prankflag"},
	 {"predicate": {"custom_model_data":4}, "model": "block/techflag"},
	 {"predicate": {"custom_model_data":5}, "model": "block/bluepekit"},
	 {"predicate": {"custom_model_data":6}, "model": "block/yellowpekit"},
	 {"predicate": {"custom_model_data":7}, "model": "block/redpekit"},
	 {"predicate": {"custom_model_data":8}, "model": "block/greenpekit"},
	 {"predicate": {"custom_model_data":9}, "model": "block/greenuni"},
	 {"predicate": {"custom_model_data":10}, "model": "block/board1"},
	 {"predicate": {"custom_model_data":11}, "model": "block/maze"},
	 {"predicate": {"custom_model_data":12}, "model": "block/steve"},
	 {"predicate": {"custom_model_data":13}, "model": "block/mic"},
	 {"predicate": {"custom_model_data":14}, "model": "block/computer"},
	 {"predicate": {"custom_model_data":15}, "model": "block/trophyone"},
	 {"predicate": {"custom_model_data":16}, "model": "block/trophyinnit"},
	 {"predicate": {"custom_model_data":17}, "model": "block/trophys"},
	 {"predicate": {"custom_model_data":18}, "model": "block/trophyb"},
	 {"predicate": {"custom_model_data":19}, "model": "block/shan"},
	 {"predicate": {"custom_model_data":20}, "model": "block/roxplz2"},
	 {"predicate": {"custom_model_data":21}, "model": "block/autumn"},
	 {"predicate": {"custom_model_data":23}, "model": "block/bex"},
	 {"predicate": {"custom_model_data":24}, "model": "block/bry"},
	 {"predicate": {"custom_model_data":25}, "model": "block/tray"},
	 {"predicate": {"custom_model_data":26}, "model": "block/posters1"},
	 {"predicate": {"custom_model_data":27}, "model": "block/posters2"},
	 {"predicate": {"custom_model_data":29}, "model": "block/careersone"},
	 {"predicate": {"custom_model_data":30}, "model": "block/careerstwo"},
	 {"predicate": {"custom_model_data":31}, "model": "block/careersthree"},
	 {"predicate": {"custom_model_data":32}, "model": "block/careersfour"},
	 {"predicate": {"custom_model_data":33}, "model": "block/pboard"},
	 {"predicate": {"custom_model_data":34}, "model": "block/dlboard"},
	 {"predicate": {"custom_model_data":35}, "model": "block/potionboard"},
	 {"predicate": {"custom_model_data":36}, "model": "block/bbeeuni"},
	 {"predicate": {"custom_model_data":37}, "model": "block/bbuni"},
	 {"predicate": {"custom_model_data":38}, "model": "block/ppuni"},
	 {"predicate": {"custom_model_data":39}, "model": "block/ccuni"}
	]
   }